gemseo_pyoptsparse/__init__.py
gemseo_pyoptsparse/algos/__init__.py
gemseo_pyoptsparse/algos/opt/__init__.py
gemseo_pyoptsparse/algos/opt/_py_opt_sparse_functions.py
gemseo_pyoptsparse/algos/opt/_py_opt_sparse_optimization_problem.py
gemseo_pyoptsparse/algos/opt/py_opt_sparse.py
gemseo_pyoptsparse/algos/opt/settings/__init__.py
gemseo_pyoptsparse/algos/opt/settings/base_py_opt_sparse_settings.py
gemseo_pyoptsparse/algos/opt/settings/slsqp.py
gemseo_pyoptsparse/algos/opt/settings/snopt.py
gemseo_pyoptsparse-1.1.1.dist-info/METADATA
gemseo_pyoptsparse-1.1.1.dist-info/WHEEL
gemseo_pyoptsparse-1.1.1.dist-info/entry_points.txt
gemseo_pyoptsparse-1.1.1.dist-info/top_level.txt
gemseo_pyoptsparse-1.1.1.dist-info/RECORD
